{
  "generated": "2025-11-20T08:53:42.502Z",
  "summary": {
    "totalExperiences": 8,
    "uniqueLearners": 5,
    "uniqueLocations": 7,
    "uniqueDomains": 16,
    "interdisciplinaryExperiences": 8
  },
  "learningHotspots": [
    {
      "location": "Central Library Makerspace",
      "count": 2,
      "domains": [
        "electronics",
        "environmental science",
        "programming",
        "data visualization"
      ],
      "types": [
        "failure",
        "experiment"
      ],
      "learners": 1,
      "coordinates": {
        "lat": 51.5074,
        "lon": -0.1278
      },
      "diversity": 4
    },
    {
      "location": "Cafe on Brick Lane",
      "count": 1,
      "domains": [
        "data visualization",
        "history",
        "cartography",
        "programming"
      ],
      "types": [
        "discovery"
      ],
      "learners": 1,
      "coordinates": {
        "lat": 51.5208,
        "lon": -0.0714
      },
      "diversity": 4
    },
    {
      "location": "Granary Square, Kings Cross",
      "count": 1,
      "domains": [
        "urban planning",
        "data visualization",
        "art",
        "sociology"
      ],
      "types": [
        "collaboration"
      ],
      "learners": 1,
      "coordinates": {
        "lat": 51.5359,
        "lon": -0.1252
      },
      "diversity": 4
    },
    {
      "location": "Shakespeare's Globe Theatre",
      "count": 1,
      "domains": [
        "literature",
        "theater",
        "architecture",
        "design"
      ],
      "types": [
        "reflection"
      ],
      "learners": 1,
      "coordinates": {
        "lat": 51.5081,
        "lon": -0.0972
      },
      "diversity": 4
    },
    {
      "location": "Shoreditch High Street",
      "count": 1,
      "domains": [
        "urban planning",
        "sociology",
        "architecture"
      ],
      "types": [
        "observation"
      ],
      "learners": 1,
      "coordinates": {
        "lat": 51.5236,
        "lon": -0.0775
      },
      "diversity": 3
    },
    {
      "location": "Borough Market",
      "count": 1,
      "domains": [
        "agriculture",
        "environmental science",
        "electronics"
      ],
      "types": [
        "insight"
      ],
      "learners": 1,
      "coordinates": {
        "lat": 51.5055,
        "lon": -0.0909
      },
      "diversity": 3
    },
    {
      "location": "Brixton Village Market",
      "count": 1,
      "domains": [
        "anthropology",
        "methodology",
        "sociology"
      ],
      "types": [
        "question"
      ],
      "learners": 1,
      "coordinates": {
        "lat": 51.4613,
        "lon": -0.1142
      },
      "diversity": 3
    }
  ],
  "interdisciplinaryConnections": [
    {
      "id": "ubi-85c14ea9-8b7b-42f3-a19b-b02feb83c99a",
      "domains": [
        "electronics",
        "environmental science",
        "programming"
      ],
      "description": "Tried connecting Arduino to city air quality sensor. Failed to get I2C communication working, but learned about protocol timing and pullup resistors.",
      "location": "Central Library Makerspace",
      "unexpected": [
        "Air quality data connects to urban planning decisions",
        "Similar to how field biologists collect distributed data"
      ]
    },
    {
      "id": "ubi-e1ab926f-0016-4bb0-ac58-11b8358b97f1",
      "domains": [
        "urban planning",
        "sociology",
        "architecture"
      ],
      "description": "Noticed people naturally gather around food truck, creating impromptu social space. Seating spillover from cafe becomes de facto public square.",
      "location": "Shoreditch High Street",
      "unexpected": [
        "Food infrastructure creates social infrastructure",
        "Temporary installations can seed permanent gathering spaces",
        "Similar to how parks need activation not just design"
      ]
    },
    {
      "id": "ubi-8c137c89-9caa-4f67-9145-e6398d194dba",
      "domains": [
        "agriculture",
        "environmental science",
        "electronics"
      ],
      "description": "Vendor explained how weather patterns affect crop timing. Realized my air quality sensor project could help farmers predict microclimates.",
      "location": "Borough Market",
      "unexpected": [
        "Urban sensors could inform urban farming",
        "Market vendors have deep environmental knowledge",
        "Technology meets traditional ecological knowledge"
      ]
    },
    {
      "id": "ubi-76f9240e-f08f-4d61-a222-b5e38c53e736",
      "domains": [
        "data visualization",
        "history",
        "cartography",
        "programming"
      ],
      "description": "Overheard two people discussing local history. Led me to discover Layers of London project - historical maps overlaid on modern city. Perfect pattern for my civic data viz.",
      "location": "Cafe on Brick Lane",
      "unexpected": [
        "Historical thinking applies to civic data",
        "Maps are time machines",
        "Local knowledge lives in conversations not databases"
      ]
    },
    {
      "id": "ubi-5626635b-e57c-4368-992f-ee6879bd38f1",
      "domains": [
        "urban planning",
        "data visualization",
        "art",
        "sociology"
      ],
      "description": "Met data artist showing real-time pedestrian flow visualizations. Discussed how my observations could become datasets for art installations.",
      "location": "Granary Square, Kings Cross",
      "unexpected": [
        "Urban planning data is artistic material",
        "Art makes invisible patterns visible",
        "Collaboration across practice boundaries"
      ]
    },
    {
      "id": "ubi-f0e2462a-1c23-4fdb-8c9f-2e0f3f9151bb",
      "domains": [
        "literature",
        "theater",
        "architecture",
        "design"
      ],
      "description": "Guide explained how Globe was designed for audience interaction - no fourth wall. Made me realize my writing treats readers as audience not participants.",
      "location": "Shakespeare's Globe Theatre",
      "unexpected": [
        "Architecture shapes narrative form",
        "Interactive theater is like interactive fiction",
        "Physical space affects storytelling possibility"
      ]
    },
    {
      "id": "ubi-98d0d059-0661-4c4a-9f33-e23ed547fef6",
      "domains": [
        "anthropology",
        "methodology",
        "sociology"
      ],
      "description": "Realized my ethnographic methods assume I'm an observer. But market vendors keep pulling me into conversations. What if participation is the method?",
      "location": "Brixton Village Market",
      "unexpected": [
        "Observation vs participation is false binary",
        "Urban fieldwork is always participatory",
        "Method emerges from place not textbook"
      ]
    },
    {
      "id": "ubi-e7884f7d-b64a-44d0-b86b-e64e67cac8bb",
      "domains": [
        "electronics",
        "environmental science",
        "programming",
        "data visualization"
      ],
      "description": "Built working prototype of air quality sensor. Used I2C lessons from previous failure. Priya offered to help visualize data.",
      "location": "Central Library Makerspace",
      "unexpected": [
        "Previous failure was necessary learning",
        "Collaboration makes projects possible",
        "Makerspace becoming community not just facility"
      ]
    }
  ],
  "domainNetwork": {
    "nodes": [
      {
        "id": "electronics",
        "size": 3
      },
      {
        "id": "environmental science",
        "size": 3
      },
      {
        "id": "programming",
        "size": 3
      },
      {
        "id": "urban planning",
        "size": 2
      },
      {
        "id": "sociology",
        "size": 3
      },
      {
        "id": "architecture",
        "size": 2
      },
      {
        "id": "agriculture",
        "size": 1
      },
      {
        "id": "data visualization",
        "size": 3
      },
      {
        "id": "history",
        "size": 1
      },
      {
        "id": "cartography",
        "size": 1
      },
      {
        "id": "art",
        "size": 1
      },
      {
        "id": "literature",
        "size": 1
      },
      {
        "id": "theater",
        "size": 1
      },
      {
        "id": "design",
        "size": 1
      },
      {
        "id": "anthropology",
        "size": 1
      },
      {
        "id": "methodology",
        "size": 1
      }
    ],
    "edges": [
      {
        "source": "electronics",
        "target": "environmental science",
        "weight": 3
      },
      {
        "source": "electronics",
        "target": "programming",
        "weight": 2
      },
      {
        "source": "environmental science",
        "target": "programming",
        "weight": 2
      },
      {
        "source": "sociology",
        "target": "urban planning",
        "weight": 2
      },
      {
        "source": "architecture",
        "target": "urban planning",
        "weight": 1
      },
      {
        "source": "architecture",
        "target": "sociology",
        "weight": 1
      },
      {
        "source": "agriculture",
        "target": "environmental science",
        "weight": 1
      },
      {
        "source": "agriculture",
        "target": "electronics",
        "weight": 1
      },
      {
        "source": "data visualization",
        "target": "history",
        "weight": 1
      },
      {
        "source": "cartography",
        "target": "data visualization",
        "weight": 1
      },
      {
        "source": "data visualization",
        "target": "programming",
        "weight": 2
      },
      {
        "source": "cartography",
        "target": "history",
        "weight": 1
      },
      {
        "source": "history",
        "target": "programming",
        "weight": 1
      },
      {
        "source": "cartography",
        "target": "programming",
        "weight": 1
      },
      {
        "source": "data visualization",
        "target": "urban planning",
        "weight": 1
      },
      {
        "source": "art",
        "target": "urban planning",
        "weight": 1
      },
      {
        "source": "art",
        "target": "data visualization",
        "weight": 1
      },
      {
        "source": "data visualization",
        "target": "sociology",
        "weight": 1
      },
      {
        "source": "art",
        "target": "sociology",
        "weight": 1
      },
      {
        "source": "literature",
        "target": "theater",
        "weight": 1
      },
      {
        "source": "architecture",
        "target": "literature",
        "weight": 1
      },
      {
        "source": "design",
        "target": "literature",
        "weight": 1
      },
      {
        "source": "architecture",
        "target": "theater",
        "weight": 1
      },
      {
        "source": "design",
        "target": "theater",
        "weight": 1
      },
      {
        "source": "architecture",
        "target": "design",
        "weight": 1
      },
      {
        "source": "anthropology",
        "target": "methodology",
        "weight": 1
      },
      {
        "source": "anthropology",
        "target": "sociology",
        "weight": 1
      },
      {
        "source": "methodology",
        "target": "sociology",
        "weight": 1
      },
      {
        "source": "data visualization",
        "target": "electronics",
        "weight": 1
      },
      {
        "source": "data visualization",
        "target": "environmental science",
        "weight": 1
      }
    ]
  },
  "locationMap": {
    "Central Library Makerspace": {
      "count": 2,
      "domains": [
        "electronics",
        "environmental science",
        "programming",
        "data visualization"
      ],
      "types": [
        "failure",
        "experiment"
      ],
      "learners": 1,
      "coordinates": {
        "lat": 51.5074,
        "lon": -0.1278
      },
      "diversity": 4
    },
    "Shoreditch High Street": {
      "count": 1,
      "domains": [
        "urban planning",
        "sociology",
        "architecture"
      ],
      "types": [
        "observation"
      ],
      "learners": 1,
      "coordinates": {
        "lat": 51.5236,
        "lon": -0.0775
      },
      "diversity": 3
    },
    "Borough Market": {
      "count": 1,
      "domains": [
        "agriculture",
        "environmental science",
        "electronics"
      ],
      "types": [
        "insight"
      ],
      "learners": 1,
      "coordinates": {
        "lat": 51.5055,
        "lon": -0.0909
      },
      "diversity": 3
    },
    "Cafe on Brick Lane": {
      "count": 1,
      "domains": [
        "data visualization",
        "history",
        "cartography",
        "programming"
      ],
      "types": [
        "discovery"
      ],
      "learners": 1,
      "coordinates": {
        "lat": 51.5208,
        "lon": -0.0714
      },
      "diversity": 4
    },
    "Granary Square, Kings Cross": {
      "count": 1,
      "domains": [
        "urban planning",
        "data visualization",
        "art",
        "sociology"
      ],
      "types": [
        "collaboration"
      ],
      "learners": 1,
      "coordinates": {
        "lat": 51.5359,
        "lon": -0.1252
      },
      "diversity": 4
    },
    "Shakespeare's Globe Theatre": {
      "count": 1,
      "domains": [
        "literature",
        "theater",
        "architecture",
        "design"
      ],
      "types": [
        "reflection"
      ],
      "learners": 1,
      "coordinates": {
        "lat": 51.5081,
        "lon": -0.0972
      },
      "diversity": 4
    },
    "Brixton Village Market": {
      "count": 1,
      "domains": [
        "anthropology",
        "methodology",
        "sociology"
      ],
      "types": [
        "question"
      ],
      "learners": 1,
      "coordinates": {
        "lat": 51.4613,
        "lon": -0.1142
      },
      "diversity": 3
    }
  }
}